data_tree/README.txt
data_tree/__init__.py
data_tree/src/__init__.py
data_tree/src/data_tree_node.c
data_tree/src/data_tree_node.cpython-37m-darwin.so
data_tree/src/data_tree_node.py
data_tree/src/data_tree_node.pyx
data_tree/src/data_tree_node_with_quick_lookup.c
data_tree/src/data_tree_node_with_quick_lookup.cpython-37m-darwin.so
data_tree/src/data_tree_node_with_quick_lookup.py
data_tree/src/data_tree_node_with_quick_lookup.pyx
data_tree-0.0.1.dist-info/METADATA
data_tree-0.0.1.dist-info/WHEEL
data_tree-0.0.1.dist-info/top_level.txt
data_tree-0.0.1.dist-info/RECORD
