Metadata-Version: 2.1
Name: data-tree
Version: 0.0.1
Summary: UNKNOWN
Home-page: https://github.com/jrhazlett/data_tree
Author: James Hazlett
Author-email: james.hazlett.python@gmail.com
License: UNKNOWN
Platform: UNKNOWN
Classifier: Programming Language :: Python :: 3
Classifier: License :: OSI Approved :: MIT License
Classifier: Operating System :: OS Independent
